MANIFEST.in
docs/Makefile
docs/build/html/_sources/hydrowizard.rst.txt
docs/build/html/_sources/hydrowizard.scripts.rst.txt
docs/build/html/_sources/index.rst.txt
docs/build/html/_sources/license.rst.txt
docs/build/html/_sources/modules.rst.txt
docs/build/html/_sources/optimize.rst.txt
docs/build/html/_sources/simulate.rst.txt
docs/make.bat
docs/source/conf.py
docs/source/hydrowizard.rst
docs/source/hydrowizard.scripts.rst
docs/source/index.rst
docs/source/license.rst
docs/source/modules.rst
docs/source/optimize.rst
docs/source/requirements.txt
docs/source/simulate.rst
hydrowizard/__init__.py
hydrowizard/basin.py
hydrowizard/db_logging.py
hydrowizard/flow.py
hydrowizard/node.py
hydrowizard/optimization.py
hydrowizard/rbf_network.py
hydrowizard/scripts/__init__.py
hydrowizard/scripts/run_optimization.py
hydrowizard/scripts/run_simulation.py
setup.py
hydrowizard-0.2.0.dist-info/LICENSE
hydrowizard-0.2.0.dist-info/METADATA
hydrowizard-0.2.0.dist-info/WHEEL
hydrowizard-0.2.0.dist-info/entry_points.txt
hydrowizard-0.2.0.dist-info/RECORD
