Metadata-Version: 2.1
Name: hydrowizard
Version: 0.2.0
Summary: HydroWizard: State-of-the-art water basin modeling, optimization, and simulation using neural networks, genetic algorithms, and DAGs.
Home-page: https://www.hydrowizard.ai
License: Other
Author: Yugdeep Bangar
Author-email: yugdeep@hydrowizard.ai
Requires-Python: >=3.10,<4.0
Classifier: License :: Other/Proprietary License
Classifier: Operating System :: OS Independent
Classifier: Programming Language :: Python :: 3
Classifier: Programming Language :: Python :: 3.10
Classifier: Programming Language :: Python :: 3.11
Classifier: Programming Language :: Python :: 3.12
Requires-Dist: PyYAML (>=6.0.1,<7.0.0)
Requires-Dist: graphviz (>=0.20.3,<0.21.0)
Requires-Dist: matplotlib (>=3.8.0,<4.0.0)
Requires-Dist: networkx (>=3.3,<4.0)
Requires-Dist: numpy (>=2.0.1,<3.0.0)
Requires-Dist: openpyxl (>=3.1.5,<4.0.0)
Requires-Dist: pandas (>=2.2.2,<3.0.0)
Requires-Dist: psycopg2-binary (>=2.9.9,<3.0.0)
Requires-Dist: pymoo (>=0.6.1.3,<0.7.0.0)
Requires-Dist: pytz (>=2024.1,<2025.0)
Requires-Dist: sqlalchemy (>=2.0.31,<3.0.0)
Requires-Dist: tqdm (>=4.66.4,<5.0.0)
Project-URL: Repository, https://github.com/yugdeep/hydrowizard
